taiga_contrib_hipchat/__init__.py
taiga_contrib_hipchat/api.py
taiga_contrib_hipchat/apps.py
taiga_contrib_hipchat/models.py
taiga_contrib_hipchat/permissions.py
taiga_contrib_hipchat/serializers.py
taiga_contrib_hipchat/signal_handlers.py
taiga_contrib_hipchat/tasks.py
taiga_contrib_hipchat/migrations/0001_initial.py
taiga_contrib_hipchat/migrations/0002_hipchathook_notify.py
taiga_contrib_hipchat/migrations/0003_auto_20150912_1109.py
taiga_contrib_hipchat/migrations/0004_auto_20160915_0724.py
taiga_contrib_hipchat/migrations/__init__.py
taiga_contrib_hipchat/templates/taiga_contrib_hipchat/change.jinja
taiga_contrib_hipchat/templates/taiga_contrib_hipchat/create.jinja
taiga_contrib_hipchat/templates/taiga_contrib_hipchat/delete.jinja
taiga_contrib_hipchat/templates/taiga_contrib_hipchat/field-diff.jinja
taiga_contrib_hipchat-5.5.1.dist-info/LICENSE
taiga_contrib_hipchat-5.5.1.dist-info/METADATA
taiga_contrib_hipchat-5.5.1.dist-info/WHEEL
taiga_contrib_hipchat-5.5.1.dist-info/top_level.txt
taiga_contrib_hipchat-5.5.1.dist-info/RECORD
