Metadata-Version: 2.1
Name: taiga-contrib-hipchat
Version: 5.5.1
Summary: The Taiga plugin for HipChat integration
Home-page: https://github.com/taigaio/taiga-contrib-hipchat
Author: Andrea Stagi
Author-email: a.stagi@nephila.it
License: AGPL
Keywords: taiga,hipchat,integration
Platform: UNKNOWN
Classifier: Programming Language :: Python
Classifier: Development Status :: 4 - Beta
Classifier: Framework :: Django
Classifier: Intended Audience :: Developers
Classifier: License :: OSI Approved :: GNU Affero General Public License v3
Classifier: Operating System :: OS Independent
Classifier: Programming Language :: Python
Classifier: Topic :: Internet :: WWW/HTTP
